Workbook

Sheet 应收实收台账
A1: 日期 | B1: 场地 | C1: 类型 | D1: 出勤名单 | E1: 应收 | F1: 实收 | G1: 现金成本 | H1: 净结余 | I1: 到账状态 | J1: 备注
A2: 2026-08-15 | B2: 环岛路音乐广场 | C2: 商演 | D2: 青宝/超子/梓渊 | E2: 1600 | F2: 1600 | G2: 0 | H2: =IF(F2="","",F2-G2) | I2: 已结清 | J2: 现结
A3: 2026-08-16 | B3: 甜蜜经济 | C3: 商演 | D3: 青宝/姝言/超子/梓渊/铭哲 | E3: 3000 | F3: 1000 | G3: 200 | H3: =IF(F3="","",F3-G3) | I3: 定金已收 | J3: 尾款待结
A6: 使用说明
A7: 1. 每场一行。『出勤名单』必填——这是分账根基（长周期统一结时按各场出勤累加，与结算时点无关）。
A8: 2. 『应收』= 本场应得收入；『实收』= 已到账金额。定金/口头约定/长周期统一结：先填应收，到账后补实收。
A9: 3. 『现金成本』= 本场实际发生的现金支出（电力/运输/餐饮/场地方分成），凭票填写。
A10: 4. 『净结余』= 应收-成本，分账时按出勤人头均分。基金平时不预扣，需要时单独记（见『基金事件』表）。

Sheet 支出流水
A1: 日期 | B1: 类目 | C1: 金额 | D1: 经手人 | E1: 性质 | F1: 备注
A2: 2026-08-16 | B2: 运输 | C2: 150 | D2: 青宝 | E2: 乐队 | F2: 运费
A3: 2026-08-16 | B3: 餐饮 | C3: 80 | D3: 超子 | E3: 垫付 | F3: 晚饭
A6: 1. 类目：电力/运输/餐饮/分账/设备维修/宣发/其他。
A7: 2. 性质：个人资产（乐手自购自持，算个人开支）→ 不占基金；乐队公共 → 基金支出；垫付 → 基金报销。
A8: 3. 判定一句话：『资产最终归谁，钱就谁出』——归个人则个人掏，归乐队共用则基金掏。

Sheet 基金事件
A1: 日期 | B1: 事由 | C1: 金额 | D1: 分摊人头 | E1: 人均 | F1: 状态 | G1: 备注
A6: 1. 基金平时余额为 0，只有出现具体需要时才凑（触发式，非每场抽成）。
A7: 2. 需要时：报金额+用途 → 全员按人头均摊 → 群收款收齐 → 支出 → 记一行，花完即清。
A8: 3. 只记：设备维修/乐队公共采购/宣发。个人资产购置不算基金。

Sheet 月度汇总
A1: 月份 | B1: 场次数 | C1: 应收合计 | D1: 实收合计 | E1: 成本合计 | F1: 净结余 | G1: 说明
A2: 2026-01 | B2: =SUMPRODUCT(--(LEFT(应收实收台账!A2:A1000,7)="2026-01")) | C2: =SUMIFS(应收实收台账!E2:E1000,应收实收台账!A2:A1000,"2026-01*") | D2: =SUMIFS(应收实收台账!F2:F1000,应收实收台账!A2:A1000,"2026-01*") | E2: =SUMIFS(应收实收台账!G2:G1000,应收实收台账!A2:A1000,"2026-01*") | F2: =IF(C2="",0,C2-E2)
A3: 2026-02 | B3: =SUMPRODUCT(--(LEFT(应收实收台账!A2:A1000,7)="2026-02")) | C3: =SUMIFS(应收实收台账!E2:E1000,应收实收台账!A2:A1000,"2026-02*") | D3: =SUMIFS(应收实收台账!F2:F1000,应收实收台账!A2:A1000,"2026-02*") | E3: =SUMIFS(应收实收台账!G2:G1000,应收实收台账!A2:A1000,"2026-02*") | F3: =IF(C3="",0,C3-E3)
A4: 2026-03 | B4: =SUMPRODUCT(--(LEFT(应收实收台账!A2:A1000,7)="2026-03")) | C4: =SUMIFS(应收实收台账!E2:E1000,应收实收台账!A2:A1000,"2026-03*") | D4: =SUMIFS(应收实收台账!F2:F1000,应收实收台账!A2:A1000,"2026-03*") | E4: =SUMIFS(应收实收台账!G2:G1000,应收实收台账!A2:A1000,"2026-03*") | F4: =IF(C4="",0,C4-E4)
A5: 2026-04 | B5: =SUMPRODUCT(--(LEFT(应收实收台账!A2:A1000,7)="2026-04")) | C5: =SUMIFS(应收实收台账!E2:E1000,应收实收台账!A2:A1000,"2026-04*") | D5: =SUMIFS(应收实收台账!F2:F1000,应收实收台账!A2:A1000,"2026-04*") | E5: =SUMIFS(应收实收台账!G2:G1000,应收实收台账!A2:A1000,"2026-04*") | F5: =IF(C5="",0,C5-E5)
A6: 2026-05 | B6: =SUMPRODUCT(--(LEFT(应收实收台账!A2:A1000,7)="2026-05")) | C6: =SUMIFS(应收实收台账!E2:E1000,应收实收台账!A2:A1000,"2026-05*") | D6: =SUMIFS(应收实收台账!F2:F1000,应收实收台账!A2:A1000,"2026-05*") | E6: =SUMIFS(应收实收台账!G2:G1000,应收实收台账!A2:A1000,"2026-05*") | F6: =IF(C6="",0,C6-E6)
A7: 2026-06 | B7: =SUMPRODUCT(--(LEFT(应收实收台账!A2:A1000,7)="2026-06")) | C7: =SUMIFS(应收实收台账!E2:E1000,应收实收台账!A2:A1000,"2026-06*") | D7: =SUMIFS(应收实收台账!F2:F1000,应收实收台账!A2:A1000,"2026-06*") | E7: =SUMIFS(应收实收台账!G2:G1000,应收实收台账!A2:A1000,"2026-06*") | F7: =IF(C7="",0,C7-E7)
A8: 2026-07 | B8: =SUMPRODUCT(--(LEFT(应收实收台账!A2:A1000,7)="2026-07")) | C8: =SUMIFS(应收实收台账!E2:E1000,应收实收台账!A2:A1000,"2026-07*") | D8: =SUMIFS(应收实收台账!F2:F1000,应收实收台账!A2:A1000,"2026-07*") | E8: =SUMIFS(应收实收台账!G2:G1000,应收实收台账!A2:A1000,"2026-07*") | F8: =IF(C8="",0,C8-E8)
A9: 2026-08 | B9: =SUMPRODUCT(--(LEFT(应收实收台账!A2:A1000,7)="2026-08")) | C9: =SUMIFS(应收实收台账!E2:E1000,应收实收台账!A2:A1000,"2026-08*") | D9: =SUMIFS(应收实收台账!F2:F1000,应收实收台账!A2:A1000,"2026-08*") | E9: =SUMIFS(应收实收台账!G2:G1000,应收实收台账!A2:A1000,"2026-08*") | F9: =IF(C9="",0,C9-E9)
A10: 2026-09 | B10: =SUMPRODUCT(--(LEFT(应收实收台账!A2:A1000,7)="2026-09")) | C10: =SUMIFS(应收实收台账!E2:E1000,应收实收台账!A2:A1000,"2026-09*") | D10: =SUMIFS(应收实收台账!F2:F1000,应收实收台账!A2:A1000,"2026-09*") | E10: =SUMIFS(应收实收台账!G2:G1000,应收实收台账!A2:A1000,"2026-09*") | F10: =IF(C10="",0,C10-E10)
A11: 2026-10 | B11: =SUMPRODUCT(--(LEFT(应收实收台账!A2:A1000,7)="2026-10")) | C11: =SUMIFS(应收实收台账!E2:E1000,应收实收台账!A2:A1000,"2026-10*") | D11: =SUMIFS(应收实收台账!F2:F1000,应收实收台账!A2:A1000,"2026-10*") | E11: =SUMIFS(应收实收台账!G2:G1000,应收实收台账!A2:A1000,"2026-10*") | F11: =IF(C11="",0,C11-E11)
A12: 2026-11 | B12: =SUMPRODUCT(--(LEFT(应收实收台账!A2:A1000,7)="2026-11")) | C12: =SUMIFS(应收实收台账!E2:E1000,应收实收台账!A2:A1000,"2026-11*") | D12: =SUMIFS(应收实收台账!F2:F1000,应收实收台账!A2:A1000,"2026-11*") | E12: =SUMIFS(应收实收台账!G2:G1000,应收实收台账!A2:A1000,"2026-11*") | F12: =IF(C12="",0,C12-E12)
A13: 2026-12 | B13: =SUMPRODUCT(--(LEFT(应收实收台账!A2:A1000,7)="2026-12")) | C13: =SUMIFS(应收实收台账!E2:E1000,应收实收台账!A2:A1000,"2026-12*") | D13: =SUMIFS(应收实收台账!F2:F1000,应收实收台账!A2:A1000,"2026-12*") | E13: =SUMIFS(应收实收台账!G2:G1000,应收实收台账!A2:A1000,"2026-12*") | F13: =IF(C13="",0,C13-E13)
A15: 1. 公式自动汇总『应收实收台账』，新增场次只需在台账加行，这里自动更新。
A16: 2. 净结余 = 应收合计 - 成本合计（分账基数）。
A17: 3. 实收合计 < 应收合计 说明还有尾款/定金未到账，需在台账追踪到账状态。
